mulensmodel-3.9.0.dist-info/RECORD
mulensmodel-3.9.0.dist-info/WHEEL
mulensmodel-3.9.0.dist-info/top_level.txt
mulensmodel-3.9.0.dist-info/METADATA
mulensmodel-3.9.0.dist-info/licenses/AUTHORS.md
mulensmodel-3.9.0.dist-info/licenses/LICENSE
MulensModel/magnificationcurve.py
MulensModel/binarylenswithshear.py
MulensModel/binarylens.py
MulensModel/.flake8
MulensModel/horizons.py
MulensModel/event.py
MulensModel/b0b1utils.py
MulensModel/version.py
MulensModel/pointlens.py
MulensModel/satelliteskycoord.py
MulensModel/limbdarkeningcoeffs.py
MulensModel/uniformcausticsampling.py
MulensModel/causticsbinary.py
MulensModel/__init__.py
MulensModel/causticsbinarywithshear.py
MulensModel/trajectory.py
MulensModel/modelparameters.py
MulensModel/model.py
MulensModel/fitdata.py
MulensModel/AdaptiveContouring.cpython-312-darwin.so
MulensModel/utils.py
MulensModel/pointlenswithshear.py
MulensModel/binarylensimports.py
MulensModel/elliputils.py
MulensModel/causticspointwithshear.py
MulensModel/mulensdata.py
MulensModel/coordinates.py
MulensModel/orbits/orbit.py
MulensModel/orbits/__init__.py
MulensModel/tests/test_Model.py
MulensModel/tests/test_Model_Parallax.py
MulensModel/tests/test_Utils.py
MulensModel/tests/test_Lens.py
MulensModel/tests/test_VBM.py
MulensModel/tests/test_MulensSystem.py
MulensModel/tests/test_MulensData.py
MulensModel/tests/fortran_files.py
MulensModel/tests/test_Caustics.py
MulensModel/tests/test_BinaryLensWithShear.py
MulensModel/tests/test_PointLensWithShear.py
MulensModel/tests/test_CausticsPointWithShear.py
MulensModel/tests/test_Event.py
MulensModel/tests/test_CausticsWithShear.py
MulensModel/tests/test_PointLens.py
MulensModel/tests/test_FitData.py
MulensModel/tests/test_Orbit.py
MulensModel/tests/test_Trajectory.py
MulensModel/tests/test_Coords.py
MulensModel/tests/test_SatelliteSkyCoord.py
MulensModel/tests/test_BinaryLens.py
MulensModel/tests/test_ModelParameters.py
MulensModel/tests/test_MagnificationCurve.py
MulensModel/tests/test_UniformCausticSampling.py
MulensModel/mulensobjects/lens.py
MulensModel/mulensobjects/__init__.py
MulensModel/mulensobjects/source.py
MulensModel/mulensobjects/mulenssystem.py
