Metadata-Version: 2.1
Name: mulensmodel
Version: 3.9.0
Summary: package for modeling gravitational microlensing events
Home-page: https://github.com/rpoleski/MulensModel
Author: Radek Poleski & Jennifer Yee
Author-email: radek.poleski@gmail.com
License: MIT
Project-URL: documentation, https://github.com/rpoleski/MulensModel
Classifier: Programming Language :: Python :: 3
Classifier: License :: OSI Approved :: MIT License
Classifier: Operating System :: OS Independent
Requires-Python: >=3.6
License-File: LICENSE
License-File: AUTHORS.md
Requires-Dist: numpy
Requires-Dist: scipy >=0.18.0
Requires-Dist: astropy >=1.2.0
Requires-Dist: matplotlib
Requires-Dist: sympy
Requires-Dist: py-cpuinfo
Requires-Dist: VBMicrolensing >=5.3.5
